psoa.py
psoa-1.0.1.data/scripts/psoa.py
psoa-1.0.1.dist-info/LICENSE.txt
psoa-1.0.1.dist-info/METADATA
psoa-1.0.1.dist-info/WHEEL
psoa-1.0.1.dist-info/top_level.txt
psoa-1.0.1.dist-info/zip-safe
psoa-1.0.1.dist-info/RECORD
