Metadata-Version: 2.1
Name: psoa
Version: 1.0.1
Summary: An implementation of the Particle Swarm Optimization algorithm
Home-page: https://github.com/XiangwenWang/psoa
Author: Xiangwen Wang
Author-email: wangxiangwen1989@gmail.com
License: BSD 2-Clause License
Keywords: pso,Particle Swarm Optimization
Platform: any
Classifier: Development Status :: 5 - Production/Stable
Classifier: Intended Audience :: Developers
Classifier: License :: OSI Approved :: BSD License
Classifier: Operating System :: OS Independent
Classifier: Programming Language :: Python :: 2
Classifier: Programming Language :: Python :: 2.7
Classifier: Programming Language :: Python :: 3
Classifier: Programming Language :: Python :: 3.4
Classifier: Programming Language :: Python :: 3.5
Classifier: Programming Language :: Python :: 3.6
Classifier: Programming Language :: Python :: 3.7
Classifier: Programming Language :: Python :: 3.8
Requires-Dist: numpy
